<?xml version="1.0" ?>
<annotation>
  <folder>frames</folder>
  <filename>frame_3158.jpg</filename>
  <size>
    <width>1280</width>
    <height>720</height>
    <depth>3</depth>
  </size>
  <object>
    <name>object_4814.0</name>
    <bndbox>
      <xmin>1127</xmin>
      <ymin>585</ymin>
      <xmax>1205</xmax>
      <ymax>640</ymax>
    </bndbox>
  </object>
  <object>
    <name>object_4810.0</name>
    <bndbox>
      <xmin>942</xmin>
      <ymin>455</ymin>
      <xmax>990</xmax>
      <ymax>707</ymax>
    </bndbox>
  </object>
  <object>
    <name>object_4811.0</name>
    <bndbox>
      <xmin>1120</xmin>
      <ymin>247</ymin>
      <xmax>1192</xmax>
      <ymax>442</ymax>
    </bndbox>
  </object>
  <object>
    <name>object_4817.0</name>
    <bndbox>
      <xmin>162</xmin>
      <ymin>655</ymin>
      <xmax>331</xmax>
      <ymax>698</ymax>
    </bndbox>
  </object>
  <object>
    <name>object_4804.0</name>
    <bndbox>
      <xmin>162</xmin>
      <ymin>655</ymin>
      <xmax>331</xmax>
      <ymax>698</ymax>
    </bndbox>
  </object>
  <object>
    <name>object_13</name>
    <bndbox>
      <xmin>13</xmin>
      <ymin>459</ymin>
      <xmax>207</xmax>
      <ymax>566</ymax>
    </bndbox>
  </object>
  <object>
    <name>object_4812.0</name>
    <bndbox>
      <xmin>42</xmin>
      <ymin>386</ymin>
      <xmax>168</xmax>
      <ymax>430</ymax>
    </bndbox>
  </object>
  <object>
    <name>object_15</name>
    <bndbox>
      <xmin>1083</xmin>
      <ymin>507</ymin>
      <xmax>1146</xmax>
      <ymax>604</ymax>
    </bndbox>
  </object>
  <object>
    <name>object_4807.0</name>
    <bndbox>
      <xmin>1056</xmin>
      <ymin>310</ymin>
      <xmax>1139</xmax>
      <ymax>466</ymax>
    </bndbox>
  </object>
  <object>
    <name>object_4818.0</name>
    <bndbox>
      <xmin>103</xmin>
      <ymin>181</ymin>
      <xmax>146</xmax>
      <ymax>314</ymax>
    </bndbox>
  </object>
  <object>
    <name>object_4</name>
    <bndbox>
      <xmin>4</xmin>
      <ymin>550</ymin>
      <xmax>136</xmax>
      <ymax>646</ymax>
    </bndbox>
  </object>
  <object>
    <name>object_4815.0</name>
    <bndbox>
      <xmin>349</xmin>
      <ymin>560</ymin>
      <xmax>514</xmax>
      <ymax>710</ymax>
    </bndbox>
  </object>
  <object>
    <name>object_7</name>
    <bndbox>
      <xmin>208</xmin>
      <ymin>84</ymin>
      <xmax>339</xmax>
      <ymax>250</ymax>
    </bndbox>
  </object>
  <object>
    <name>object_4808.0</name>
    <bndbox>
      <xmin>877</xmin>
      <ymin>447</ymin>
      <xmax>931</xmax>
      <ymax>690</ymax>
    </bndbox>
  </object>
  <object>
    <name>object_4809.0</name>
    <bndbox>
      <xmin>360</xmin>
      <ymin>66</ymin>
      <xmax>489</xmax>
      <ymax>122</ymax>
    </bndbox>
  </object>
</annotation>
