<?xml version="1.0" ?>
<annotation>
  <folder>frames</folder>
  <filename>frame_4725.jpg</filename>
  <size>
    <width>1280</width>
    <height>720</height>
    <depth>3</depth>
  </size>
  <object>
    <name>object_4814.0</name>
    <bndbox>
      <xmin>1110</xmin>
      <ymin>265</ymin>
      <xmax>1171</xmax>
      <ymax>415</ymax>
    </bndbox>
  </object>
  <object>
    <name>object_4810.0</name>
    <bndbox>
      <xmin>725</xmin>
      <ymin>54</ymin>
      <xmax>914</xmax>
      <ymax>141</ymax>
    </bndbox>
  </object>
  <object>
    <name>object_4811.0</name>
    <bndbox>
      <xmin>534</xmin>
      <ymin>194</ymin>
      <xmax>647</xmax>
      <ymax>386</ymax>
    </bndbox>
  </object>
  <object>
    <name>object_4817.0</name>
    <bndbox>
      <xmin>493</xmin>
      <ymin>81</ymin>
      <xmax>659</xmax>
      <ymax>124</ymax>
    </bndbox>
  </object>
  <object>
    <name>object_4804.0</name>
    <bndbox>
      <xmin>493</xmin>
      <ymin>81</ymin>
      <xmax>659</xmax>
      <ymax>124</ymax>
    </bndbox>
  </object>
  <object>
    <name>object_13</name>
    <bndbox>
      <xmin>316</xmin>
      <ymin>594</ymin>
      <xmax>519</xmax>
      <ymax>714</ymax>
    </bndbox>
  </object>
  <object>
    <name>object_4812.0</name>
    <bndbox>
      <xmin>-2</xmin>
      <ymin>286</ymin>
      <xmax>130</xmax>
      <ymax>407</ymax>
    </bndbox>
  </object>
  <object>
    <name>object_15</name>
    <bndbox>
      <xmin>1122</xmin>
      <ymin>590</ymin>
      <xmax>1200</xmax>
      <ymax>628</ymax>
    </bndbox>
  </object>
  <object>
    <name>object_4807.0</name>
    <bndbox>
      <xmin>1117</xmin>
      <ymin>172</ymin>
      <xmax>1160</xmax>
      <ymax>297</ymax>
    </bndbox>
  </object>
  <object>
    <name>object_4818.0</name>
    <bndbox>
      <xmin>891</xmin>
      <ymin>614</ymin>
      <xmax>1074</xmax>
      <ymax>710</ymax>
    </bndbox>
  </object>
  <object>
    <name>object_4</name>
    <bndbox>
      <xmin>15</xmin>
      <ymin>591</ymin>
      <xmax>131</xmax>
      <ymax>642</ymax>
    </bndbox>
  </object>
  <object>
    <name>object_4815.0</name>
    <bndbox>
      <xmin>569</xmin>
      <ymin>97</ymin>
      <xmax>725</xmax>
      <ymax>159</ymax>
    </bndbox>
  </object>
  <object>
    <name>object_7</name>
    <bndbox>
      <xmin>669</xmin>
      <ymin>668</ymin>
      <xmax>874</xmax>
      <ymax>720</ymax>
    </bndbox>
  </object>
  <object>
    <name>object_4808.0</name>
    <bndbox>
      <xmin>1137</xmin>
      <ymin>421</ymin>
      <xmax>1232</xmax>
      <ymax>575</ymax>
    </bndbox>
  </object>
  <object>
    <name>object_4809.0</name>
    <bndbox>
      <xmin>152</xmin>
      <ymin>76</ymin>
      <xmax>283</xmax>
      <ymax>131</ymax>
    </bndbox>
  </object>
</annotation>
