<?xml version="1.0" ?>
<annotation>
  <folder>frames</folder>
  <filename>frame_8563.jpg</filename>
  <size>
    <width>1280</width>
    <height>720</height>
    <depth>3</depth>
  </size>
  <object>
    <name>object_4814.0</name>
    <bndbox>
      <xmin>1123</xmin>
      <ymin>600</ymin>
      <xmax>1199</xmax>
      <ymax>654</ymax>
    </bndbox>
  </object>
  <object>
    <name>object_4810.0</name>
    <bndbox>
      <xmin>1097</xmin>
      <ymin>510</ymin>
      <xmax>1187</xmax>
      <ymax>542</ymax>
    </bndbox>
  </object>
  <object>
    <name>object_4811.0</name>
    <bndbox>
      <xmin>306</xmin>
      <ymin>46</ymin>
      <xmax>451</xmax>
      <ymax>67</ymax>
    </bndbox>
  </object>
  <object>
    <name>object_4817.0</name>
    <bndbox>
      <xmin>609</xmin>
      <ymin>59</ymin>
      <xmax>673</xmax>
      <ymax>189</ymax>
    </bndbox>
  </object>
  <object>
    <name>object_4804.0</name>
    <bndbox>
      <xmin>609</xmin>
      <ymin>59</ymin>
      <xmax>673</xmax>
      <ymax>189</ymax>
    </bndbox>
  </object>
  <object>
    <name>object_13</name>
    <bndbox>
      <xmin>651</xmin>
      <ymin>482</ymin>
      <xmax>844</xmax>
      <ymax>667</ymax>
    </bndbox>
  </object>
  <object>
    <name>object_4812.0</name>
    <bndbox>
      <xmin>52</xmin>
      <ymin>394</ymin>
      <xmax>104</xmax>
      <ymax>544</ymax>
    </bndbox>
  </object>
  <object>
    <name>object_15</name>
    <bndbox>
      <xmin>376</xmin>
      <ymin>500</ymin>
      <xmax>514</xmax>
      <ymax>683</ymax>
    </bndbox>
  </object>
  <object>
    <name>object_4807.0</name>
    <bndbox>
      <xmin>505</xmin>
      <ymin>81</ymin>
      <xmax>586</xmax>
      <ymax>204</ymax>
    </bndbox>
  </object>
  <object>
    <name>object_4818.0</name>
    <bndbox>
      <xmin>299</xmin>
      <ymin>494</ymin>
      <xmax>366</xmax>
      <ymax>700</ymax>
    </bndbox>
  </object>
  <object>
    <name>object_4</name>
    <bndbox>
      <xmin>32</xmin>
      <ymin>608</ymin>
      <xmax>202</xmax>
      <ymax>669</ymax>
    </bndbox>
  </object>
  <object>
    <name>object_4815.0</name>
    <bndbox>
      <xmin>1097</xmin>
      <ymin>316</ymin>
      <xmax>1145</xmax>
      <ymax>436</ymax>
    </bndbox>
  </object>
  <object>
    <name>object_7</name>
    <bndbox>
      <xmin>440</xmin>
      <ymin>670</ymin>
      <xmax>656</xmax>
      <ymax>699</ymax>
    </bndbox>
  </object>
  <object>
    <name>object_4808.0</name>
    <bndbox>
      <xmin>445</xmin>
      <ymin>366</ymin>
      <xmax>737</xmax>
      <ymax>426</ymax>
    </bndbox>
  </object>
  <object>
    <name>object_4809.0</name>
    <bndbox>
      <xmin>79</xmin>
      <ymin>208</ymin>
      <xmax>89</xmax>
      <ymax>277</ymax>
    </bndbox>
  </object>
</annotation>
